bromodels/__init__.py
bromodels/_version.py
bromodels/GTM/GTM_LITHO_CLASS_table.csv
bromodels/GTM/GTM_STR_UNIT_table.csv
bromodels/GTM/GeoTop.py
bromodels/GTM/__init__.py
bromodels/GTM/data.py
bromodels/HGM/HGM_STR_table.csv
bromodels/HGM/Regis.py
bromodels/HGM/__init__.py
bromodels/HGM/data.py
bromodels-0.0.1.dist-info/LICENSE
bromodels-0.0.1.dist-info/METADATA
bromodels-0.0.1.dist-info/WHEEL
bromodels-0.0.1.dist-info/top_level.txt
bromodels-0.0.1.dist-info/RECORD
