Metadata-Version: 2.1
Name: bromodels
Version: 0.0.1
Summary: The GEOTOP and REGIS data downloaded from the DINOloket OPeNDAP server.
Project-URL: repository, https://github.com/cemsbv/bromodels
Keywords: visualizing
Requires-Python: >=3.9
License-File: LICENSE
Requires-Dist: matplotlib >=3.3.3
Requires-Dist: xarray[accel,io] >=2024.1.0
Provides-Extra: 3d
Requires-Dist: pyvista ; extra == '3d'
Provides-Extra: docs
Requires-Dist: ipython ==7.30.1 ; extra == 'docs'
Requires-Dist: Sphinx ==6.1.3 ; extra == 'docs'
Requires-Dist: sphinx-autodoc-typehints ==1.22.0 ; extra == 'docs'
Requires-Dist: asteroid-sphinx-theme ==0.0.3 ; extra == 'docs'
Requires-Dist: sphinx-rtd-theme ==1.2.0 ; extra == 'docs'
Requires-Dist: m2r2 ==0.3.2 ; extra == 'docs'
Provides-Extra: lint
Requires-Dist: black ; extra == 'lint'
Requires-Dist: isort ; extra == 'lint'
Provides-Extra: test
Requires-Dist: coveralls ; extra == 'test'
Requires-Dist: pytest ; extra == 'test'
